laporte_mqtt/__init__.py
laporte_mqtt/__main__.py
laporte_mqtt/argparser.py
laporte_mqtt/client.py
laporte_mqtt/config.py
laporte_mqtt/laporte.py
laporte_mqtt/logger.py
laporte_mqtt/main.py
laporte_mqtt/metrics.py
laporte_mqtt/mqtt.py
laporte_mqtt/version.py
laporte_mqtt-0.3.0.dist-info/LICENSE
laporte_mqtt-0.3.0.dist-info/METADATA
laporte_mqtt-0.3.0.dist-info/WHEEL
laporte_mqtt-0.3.0.dist-info/entry_points.txt
laporte_mqtt-0.3.0.dist-info/top_level.txt
laporte_mqtt-0.3.0.dist-info/RECORD
