Metadata-Version: 2.1
Name: laporte-mqtt
Version: 0.3.0
Summary: MQTT connector for Laporte.
Home-page: https://github.com/vinklat/laporte-mqtt
Author: Václav Vinklát
Author-email: vin@email.cz
License: UNKNOWN
Platform: UNKNOWN
Classifier: Programming Language :: Python :: 3
Classifier: License :: OSI Approved :: MIT License
Classifier: Operating System :: OS Independent
Requires-Dist: python-socketio[client]
Requires-Dist: paho-mqtt
Requires-Dist: pyyaml
Requires-Dist: prometheus-client
Requires-Dist: laporte
